pricefeed/__init__.py
pricefeed/ticker.py
pricefeed-0.1.3.dist-info/LICENSE.txt
pricefeed-0.1.3.dist-info/METADATA
pricefeed-0.1.3.dist-info/WHEEL
pricefeed-0.1.3.dist-info/top_level.txt
pricefeed-0.1.3.dist-info/RECORD
