Metadata-Version: 2.2
Name: pricefeed
Version: 0.1.3
Summary: A generic pricefeed generator with configurable deliveries and statistical info on prices generated.
Author-email: Toon Leijtens <toon.leijtens@gmail.com>
Maintainer-email: Toon Leijtens <toon.leijtens@gmail.com>
License: MIT License
Keywords: pricefeed,simulator,stock,statistics,price,simulation
License-File: LICENSE.txt
